reprfunc.py
reprfunc-0.2.0.dist-info/LICENSE.txt
reprfunc-0.2.0.dist-info/WHEEL
reprfunc-0.2.0.dist-info/METADATA
reprfunc-0.2.0.dist-info/RECORD
