Metadata-Version: 2.1
Name: reprfunc
Version: 0.2.0
Summary: Utilities for making useful string representations of objects.
Author-email: Kale Kundert <kale@thekunderts.net>
Requires-Python: ~=3.7
Classifier: Programming Language :: Python :: 3.7
Requires-Dist: sphinx ; extra == "doc"
Requires-Dist: sphinx_rtd_theme ; extra == "doc"
Requires-Dist: autoclasstoc ; extra == "doc"
Requires-Dist: pytest ; extra == "test"
Requires-Dist: pytest-cov ; extra == "test"
Requires-Dist: parametrize_from_file ; extra == "test"
Requires-Dist: voluptuous ; extra == "test"
Requires-Dist: coveralls ; extra == "test"
Project-URL: Bug Tracker, https://github.com/kalekundert/reprfunc/issues
Project-URL: Continuous Integration, https://github.com/kalekundert/reprfunc/actions
Project-URL: Documentation, https://reprfunc.readthedocs.io/en/latest/
Project-URL: Test Coverage, https://coveralls.io/github/kalekundert/reprfunc
Project-URL: Version Control, https://github.com/kalekundert/reprfunc
Provides-Extra: doc
Provides-Extra: test
